enki/__init__.py
enki_database-0.1.0.dist-info/LICENSE
enki_database-0.1.0.dist-info/METADATA
enki_database-0.1.0.dist-info/WHEEL
enki_database-0.1.0.dist-info/entry_points.txt
enki_database-0.1.0.dist-info/RECORD
